rosdomofon/__init__.py
rosdomofon/bitrixWork.py
rosdomofon/kafka_client.py
rosdomofon/kafka_example.py
rosdomofon/models.py
rosdomofon/rosdomofon.py
rosdomofon-0.1.16.1.dist-info/METADATA
rosdomofon-0.1.16.1.dist-info/WHEEL
rosdomofon-0.1.16.1.dist-info/top_level.txt
rosdomofon-0.1.16.1.dist-info/RECORD
