Metadata-Version: 2.4
Name: rosdomofon
Version: 0.1.16.1
Summary: ORM для работы с API РосДомофон
Project-URL: Homepage, https://github.com/darkClaw921/rosdomofon
Project-URL: Documentation, https://github.com/darkClaw921/rosdomofon
Project-URL: Repository, https://github.com/darkClaw921/rosdomofon.git
Project-URL: Bug Tracker, https://github.com/darkClaw921/rosdomofon/issues
Project-URL: Changelog, https://github.com/darkClaw921/rosdomofon/blob/master/CHANGELOG.md
Requires-Python: >=3.12
Requires-Dist: pydantic>=2.0.0
Requires-Dist: requests>=2.28.0
Requires-Dist: loguru>=0.7.0
Requires-Dist: python-dotenv>=1.1.1
Requires-Dist: kafka-python>=2.0.0
